google/cloud/compute_v1beta/__init__.py
google/cloud/compute_v1beta/gapic_metadata.json
google/cloud/compute_v1beta/gapic_version.py
google/cloud/compute_v1beta/py.typed
google/cloud/compute_v1beta/services/__init__.py
google/cloud/compute_v1beta/services/accelerator_types/__init__.py
google/cloud/compute_v1beta/services/accelerator_types/client.py
google/cloud/compute_v1beta/services/accelerator_types/pagers.py
google/cloud/compute_v1beta/services/accelerator_types/transports/__init__.py
google/cloud/compute_v1beta/services/accelerator_types/transports/base.py
google/cloud/compute_v1beta/services/accelerator_types/transports/rest.py
google/cloud/compute_v1beta/services/accelerator_types/transports/rest_base.py
google/cloud/compute_v1beta/services/addresses/__init__.py
google/cloud/compute_v1beta/services/addresses/client.py
google/cloud/compute_v1beta/services/addresses/pagers.py
google/cloud/compute_v1beta/services/addresses/transports/__init__.py
google/cloud/compute_v1beta/services/addresses/transports/base.py
google/cloud/compute_v1beta/services/addresses/transports/rest.py
google/cloud/compute_v1beta/services/addresses/transports/rest_base.py
google/cloud/compute_v1beta/services/advice/__init__.py
google/cloud/compute_v1beta/services/advice/client.py
google/cloud/compute_v1beta/services/advice/transports/__init__.py
google/cloud/compute_v1beta/services/advice/transports/base.py
google/cloud/compute_v1beta/services/advice/transports/rest.py
google/cloud/compute_v1beta/services/advice/transports/rest_base.py
google/cloud/compute_v1beta/services/autoscalers/__init__.py
google/cloud/compute_v1beta/services/autoscalers/client.py
google/cloud/compute_v1beta/services/autoscalers/pagers.py
google/cloud/compute_v1beta/services/autoscalers/transports/__init__.py
google/cloud/compute_v1beta/services/autoscalers/transports/base.py
google/cloud/compute_v1beta/services/autoscalers/transports/rest.py
google/cloud/compute_v1beta/services/autoscalers/transports/rest_base.py
google_cloud_compute_v1beta-0.6.0.dist-info/licenses/LICENSE
google_cloud_compute_v1beta-0.6.0.dist-info/METADATA
google_cloud_compute_v1beta-0.6.0.dist-info/WHEEL
google_cloud_compute_v1beta-0.6.0.dist-info/top_level.txt
google_cloud_compute_v1beta-0.6.0.dist-info/RECORD
